.gitignore
README.md
setup.py
chardetails/__init__.py
chardetails/core.py
chardetails.egg-info/PKG-INFO
chardetails.egg-info/SOURCES.txt
chardetails.egg-info/dependency_links.txt
chardetails.egg-info/not-zip-safe
chardetails.egg-info/requires.txt
chardetails.egg-info/top_level.txt
chardetails/templates/chardetails.html
chardetails/tests/__init__.py
chardetails/tests/chardetails_test.py