Metadata-Version: 1.0
Name: chardetails
Version: 0.3
Summary: Unicode character details Library
Home-page: http://silpa.org.in/chardetails
Author: Santhosh Thottingal
Author-email: santhosh.thottingal@gmail.com
License: LGPL-3.0
Platform: UNKNOWN
